{
  "index.html#page-top": "index.html#es/page-top",
  "#page-top": "#es/page-top",

  "index.html#surfboards" : "index.html#es/surfboards",
  "index.html#makers" : "index.html#es/makers",
  "inspirations.html" : "inspirations.html#es",
  "index.html#manifest" : "index.html#es/manifest",

  "surfboards.html#lolSeries" : "surfboards.html#es/lolSeries",


  "Hello !"
  :"Hola !",
  "Example 2"  							: "tei'än ve'en",
  "Example 3"  							: "teiä vede",
  "Example 4"  							: "teirän veren",
  "Example 5"  							: "teilän velen",
  "Example 6"  							: "teijjän vejen",
  "Example 7"  							: "teidän veden",
  "Example 8"  							: "teitän veten",
  "Example 9"  							: "teiðän veðen",
  "Example 10" 							: "teidhän vethen",
  "Dynamic Content" 				: "Your browser window is %s x %s",
  "Ordered Dynamic Content" : "%2$s is the height of your browser window, and %1$s is the width.",
  "HTML Content"            : "Your browser window is <b><i>%s</i></b> x <b><i>%s</i></b>"
}
