{
  "defaultSerie": "research",
  "series": {
    "research": {
      "name": "Research series",
      "description": {
        "es":"Tablas de prueba/error, customizadas u otras rarezas.",
        "en":"Trial & error, customized u other strange surfboards",
        "gl":"Táboas de proba/erro, customizadas ou outras rarezas"
      },
      "defaultBoard": "singlesimmons",
      "boards": {
        "singlesimmons": {
          "title":"Singlesimmons",
          "description":{
            "es":"Una minisimmons single de cóncavo simple. Con núcleo de EPX y madera de obeche rematado en aceite, lasur y barniz",
            "en":"A single minisimmons with simple concave.  EPX core and obeche wood finished with oil, lasure and barnish",
            "gl":"Unha minisimmons single de cóncavo simple. Con núcleo de EPX e madeira de obeche rematado en aceite, lasur e barniz"
          },
          "fins": "Single fin (US-BOX)",
          "sizes": [152,0,0],
          "weight": [3100],
          "pricing": false
        },
        "spaceoddity": {
          "title":"Space oddity",
          "description":{
            "es":"Paulownia con cámara. Con glaseado final en resina epoxi.",
            "en":"Chambered paulownia. Glassed with epoxy resin.",
            "gl":"Paulownia con cámara. Con glaseado final en resina epoxi"
          },
          "fins": "Single fin (US-BOX)",
          "sizes": [182,0,0],
          "weight": [4100],
          "pricing": false
        },
        "tablon1": {
          "title":"Minimal #1",
          "description":{
            "es":"Minimalibú. Con núcleo de EPX y contrachapado de okumen rematada en aceite, lasur y barniz",
            "en":"Minimalibu. EPX core and okumen plywood finished with oil, lasure and barnish",
            "gl":"Minimalibú. Con núcleo de EPX e contrachapado de okumen rematada en aceite, lasur e barniz"
          },
          "fins": "Single fin (US-BOX)",
          "sizes": [213,0,0],
          "weight": [5200],
          "pricing": false
        }
      }
    },

    "2_series": {
      "name": "2 Series",
      "description": {
        "es":"A tablablabblabla",
        "en":"A tablablabblabla",
        "gl":"A tablablabblabla"
      },
      "defaultBoard": "lol",
      "boards": []
    },

    "custom_series": {
      "name": "Custom Series",
      "description": "",
      "defaultBoard": "lol",
      "boards": []
    }
  }
}
